odootools_openapi/__init__.py
odootools_openapi/api.py
odootools_openapi/command.py
odootools_openapi/format.py
odootools_openapi/loading.py
odootools_openapi/objects.py
odootools_openapi/rendering.py
odootools_openapi/utils.py
odootools_openapi/orm/__init__.py
odootools_openapi/orm/model.py
odootools_openapi/orm/fields/__init__.py
odootools_openapi/orm/fields/array.py
odootools_openapi/orm/fields/base.py
odootools_openapi/orm/fields/boolean.py
odootools_openapi/orm/fields/int.py
odootools_openapi/orm/fields/string.py
tests/__init__.py
tests/fixtures.py
tests/test_command.py
tests/test_controllers.py
tests/test_jinja.py
tests/test_loading.py
tests/test_orm.py
tests/test_parameters.py
tests/test_security_schemes.py
tests/test_utils.py
odootools_openapi-0.1.0.dist-info/METADATA
odootools_openapi-0.1.0.dist-info/WHEEL
odootools_openapi-0.1.0.dist-info/entry_points.txt
odootools_openapi-0.1.0.dist-info/top_level.txt
odootools_openapi-0.1.0.dist-info/RECORD
