Metadata-Version: 2.1
Name: odootools-openapi
Version: 0.1.0
Summary: Odoo Tools Rest
Home-page: https://odoo-tools.readthedocs.io
Author: Loïc Faure-Lacroix <lamerstar@gmail.com>
Author-email: lamerstar@gmail.com
Project-URL: Source, https://github.com/llacroix/odoo-tools-rest
Project-URL: Documentation, https://odoo-tools-rest.readthedocs.io
Classifier: Programming Language :: Python :: 3
Classifier: License :: OSI Approved :: MIT License
Classifier: Operating System :: OS Independent
Requires-Python: >=3.6
Requires-Dist: openapi3
Requires-Dist: requests
Requires-Dist: click
Requires-Dist: jinja2
Provides-Extra: docs
Requires-Dist: sphinx ; extra == 'docs'
Requires-Dist: furo ; extra == 'docs'
Requires-Dist: sphinx-argparse ; extra == 'docs'
Requires-Dist: sphinx-click ; extra == 'docs'
Requires-Dist: sphinxcontrib.asciinema ; extra == 'docs'
Provides-Extra: test
Requires-Dist: mock ; extra == 'test'
Requires-Dist: pytest ; extra == 'test'
Requires-Dist: pytest-cov ; extra == 'test'
